{
  "height": 10,
  "width": 10,
  "tileheight": 16,
  "tilewidth": 16,
  "version": 1.6,
  "tiledversion": "1.10.2",
  "orientation": "orthogonal",
  "renderorder": "right-down",
  "type": "map",
  "layers": [
    {
      "type": "tilelayer",
      "name": "Ground",
      "x": 0,
      "y": 0,
      "width": 10,
      "height": 10,
      "visible": true,
      "opacity": 1,
      "data": [
        1,
        1,
        1,
        1,
        1,
        1,
        1,
        1,
        1,
        1,
        1,
        1,
        1,
        1,
        1,
        1,
        1,
        1,
        1,
        1,
        1,
        1,
        1,
        1,
        1,
        1,
        1,
        1,
        1,
        1,
        1,
        1,
        1,
        1,
        1,
        1,
        1,
        1,
        1,
        1,
        1,
        1,
        1,
        1,
        1,
        1,
        1,
        1,
        1,
        1,
        1,
        1,
        1,
        1,
        1,
        1,
        1,
        1,
        1,
        1,
        1,
        1,
        1,
        1,
        1,
        1,
        1,
        1,
        1,
        1,
        1,
        1,
        1,
        1,
        1,
        1,
        1,
        1,
        1,
        1,
        1,
        1,
        1,
        1,
        1,
        1,
        1,
        1,
        1,
        1,
        1,
        1,
        1,
        1,
        1,
        1,
        1,
        1,
        1,
        1
      ]
    }
  ],
  "tilesets": [
    {
      "firstgid": 1,
      "columns": 10,
      "image": "tileset_pastel.png",
      "imageheight": 160,
      "imagewidth": 160,
      "margin": 0,
      "name": "tileset_pastel",
      "spacing": 0,
      "tilecount": 100,
      "tileheight": 16,
      "tilewidth": 16,
      "type": "tileset",
      "version": "1.10"
    }
  ]
}